Metadata-Version: 2.4
Name: django-cookie-consent-fwd
Version: 0.6.3
Summary: Django cookie consent application
Author-email: Informatika Mihelac <bmihelac@mihelac.org>
License: Django Cookie Consent FWD
Project-URL: Source Code (fork), https://github.com/FWDhr/django-cookie-consent-fwd
Project-URL: Documentation, https://django-cookie-consent.readthedocs.io/en/latest/
Project-URL: Changelog, https://github.com/jazzband/django-cookie-consent/blob/master/docs/changelog.rst
Project-URL: Bug Tracker, https://github.com/jazzband/django-cookie-consent/issues
Project-URL: Source Code, https://github.com/jazzband/django-cookie-consent
Keywords: cookies,cookie-consent,cookie bar
Classifier: Development Status :: 4 - Beta
Classifier: Framework :: Django
Classifier: Framework :: Django :: 4.2
Classifier: Framework :: Django :: 5.0
Classifier: Intended Audience :: Developers
Classifier: License :: OSI Approved :: BSD License
Classifier: Operating System :: Unix
Classifier: Operating System :: MacOS
Classifier: Operating System :: Microsoft :: Windows
Classifier: Operating System :: OS Independent
Classifier: Programming Language :: Python :: 3.8
Classifier: Programming Language :: Python :: 3.9
Classifier: Programming Language :: Python :: 3.10
Classifier: Programming Language :: Python :: 3.11
Classifier: Programming Language :: Python :: 3.12
Classifier: Topic :: Software Development :: Libraries :: Python Modules
Requires-Python: >=3.8
License-File: LICENSE
License-File: AUTHORS
Requires-Dist: django>=4.2
Requires-Dist: django-appconf
Requires-Dist: django-modeltranslation>=0.18.0
Provides-Extra: tests
Requires-Dist: pytest; extra == "tests"
Requires-Dist: pytest-django; extra == "tests"
Requires-Dist: pytest-playwright; extra == "tests"
Requires-Dist: tox; extra == "tests"
Requires-Dist: isort; extra == "tests"
Requires-Dist: black; extra == "tests"
Requires-Dist: flake8; extra == "tests"
Provides-Extra: coverage
Requires-Dist: pytest-cov; extra == "coverage"
Provides-Extra: docs
Requires-Dist: sphinx; extra == "docs"
Requires-Dist: sphinx-rtd-theme; extra == "docs"
Provides-Extra: release
Requires-Dist: tbump; extra == "release"
Dynamic: license-file
